{
  "dcmjs-org/dcmjs|babel/babel|17879|c6a8929f20dc509866b3685607b55bda04aff372": {
    "watched_repo": "dcmjs-org/dcmjs",
    "dep_repo": "babel/babel",
    "dep_package": "@babel/runtime-corejs3",
    "pr_number": 17879,
    "pr_sha": "c6a8929f20dc509866b3685607b55bda04aff372",
    "pr_title": "fix(parser): correctly disambiguate typescript arrow return type in t…",
    "pr_url": "https://github.com/babel/babel/pull/17879",
    "result": "skipped",
    "tested_at": "2026-03-19T20:26:09.471Z",
    "run_url": "https://github.com/pieper/forewarn/actions/runs/23315355333"
  },
  "dcmjs-org/dcmjs|babel/babel|17624|203aa10784878b2cbb0bc06407772df4c3896273": {
    "watched_repo": "dcmjs-org/dcmjs",
    "dep_repo": "babel/babel",
    "dep_package": "@babel/runtime-corejs3",
    "pr_number": 17624,
    "pr_sha": "203aa10784878b2cbb0bc06407772df4c3896273",
    "pr_title": "Add parse support for the 'structs' proposal (only non-shared)",
    "pr_url": "https://github.com/babel/babel/pull/17624",
    "result": "skipped",
    "tested_at": "2026-03-19T20:48:06.579Z",
    "run_url": "https://github.com/pieper/forewarn/actions/runs/23316196247"
  },
  "dcmjs-org/dcmjs|babel/babel|17865|6a869b9b0eb0bdda3ce3941feae8d03f93d9d50e": {
    "watched_repo": "dcmjs-org/dcmjs",
    "dep_repo": "babel/babel",
    "dep_package": "@babel/runtime-corejs3",
    "pr_number": 17865,
    "pr_sha": "6a869b9b0eb0bdda3ce3941feae8d03f93d9d50e",
    "pr_title": "Fix(parser): flow parser small fixes",
    "pr_url": "https://github.com/babel/babel/pull/17865",
    "result": "failure",
    "tested_at": "2026-03-19T21:04:30.083Z",
    "run_url": "https://github.com/pieper/forewarn/actions/runs/23316848529"
  },
  "dcmjs-org/dcmjs|babel/babel|17886|744f239fba939ee369712aa8cf004340d4facca3": {
    "watched_repo": "dcmjs-org/dcmjs",
    "dep_repo": "babel/babel",
    "dep_package": "@babel/runtime-corejs3",
    "pr_number": 17886,
    "pr_sha": "744f239fba939ee369712aa8cf004340d4facca3",
    "pr_title": "Clean up the logic of some helper packages",
    "pr_url": "https://github.com/babel/babel/pull/17886",
    "result": "skipped",
    "tested_at": "2026-03-19T21:28:06.955Z",
    "run_url": "https://github.com/pieper/forewarn/actions/runs/23317755868"
  },
  "dcmjs-org/dcmjs|babel/babel|17889|ad3780997b8f6d1b3c8d66f701107408e97231a3": {
    "watched_repo": "dcmjs-org/dcmjs",
    "dep_repo": "babel/babel",
    "dep_package": "@babel/runtime-corejs3",
    "pr_number": 17889,
    "pr_sha": "ad3780997b8f6d1b3c8d66f701107408e97231a3",
    "pr_title": "Update test262",
    "pr_url": "https://github.com/babel/babel/pull/17889",
    "result": "skipped",
    "tested_at": "2026-03-20T02:59:19.227Z",
    "run_url": "https://github.com/pieper/forewarn/actions/runs/23327162498"
  },
  "dcmjs-org/dcmjs|babel/babel|17848|90a11e892ee1ff5294615dc6732730544fdc18c0": {
    "watched_repo": "dcmjs-org/dcmjs",
    "dep_repo": "babel/babel",
    "dep_package": "@babel/runtime-corejs3",
    "pr_number": 17848,
    "pr_sha": "90a11e892ee1ff5294615dc6732730544fdc18c0",
    "pr_title": "Optimize combined object rest and spread operations (Issue #3840)",
    "pr_url": "https://github.com/babel/babel/pull/17848",
    "result": "skipped",
    "tested_at": "2026-03-21T02:54:48.600Z",
    "run_url": "https://github.com/pieper/forewarn/actions/runs/23370509775"
  },
  "dcmjs-org/dcmjs|babel/babel|17785|b6e68fa892abbfa526baec3e578f0383cdc753dd": {
    "watched_repo": "dcmjs-org/dcmjs",
    "dep_repo": "babel/babel",
    "dep_package": "@babel/runtime-corejs3",
    "pr_number": 17785,
    "pr_sha": "b6e68fa892abbfa526baec3e578f0383cdc753dd",
    "pr_title": "Parse partial-application  version",
    "pr_url": "https://github.com/babel/babel/pull/17785",
    "result": "skipped",
    "tested_at": "2026-03-22T03:03:59.617Z",
    "run_url": "https://github.com/pieper/forewarn/actions/runs/23394442024"
  },
  "dcmjs-org/dcmjs|babel/babel|17864|d282a8f4e07ad762c57348b0006ec80ea761cd4e": {
    "watched_repo": "dcmjs-org/dcmjs",
    "dep_repo": "babel/babel",
    "dep_package": "@babel/runtime-corejs3",
    "pr_number": 17864,
    "pr_sha": "d282a8f4e07ad762c57348b0006ec80ea761cd4e",
    "pr_title": "fix: preserve TDZ for const/let ForDeclaration in for-await-of transform",
    "pr_url": "https://github.com/babel/babel/pull/17864",
    "result": "skipped",
    "tested_at": "2026-03-23T03:04:15.971Z",
    "run_url": "https://github.com/pieper/forewarn/actions/runs/23419612444"
  },
  "dcmjs-org/dcmjs|babel/babel|17817|d52021eead6ad78f7d896bf94013ff746fa50879": {
    "watched_repo": "dcmjs-org/dcmjs",
    "dep_repo": "babel/babel",
    "dep_package": "@babel/runtime-corejs3",
    "pr_number": 17817,
    "pr_sha": "d52021eead6ad78f7d896bf94013ff746fa50879",
    "pr_title": "Import bytes proposal",
    "pr_url": "https://github.com/babel/babel/pull/17817",
    "result": "skipped",
    "tested_at": "2026-03-24T03:00:44.505Z",
    "run_url": "https://github.com/pieper/forewarn/actions/runs/23470982163"
  },
  "dcmjs-org/dcmjs|babel/babel|17878|fa796831861231d8496eb44dd85362d2b6f04cae": {
    "watched_repo": "dcmjs-org/dcmjs",
    "dep_repo": "babel/babel",
    "dep_package": "@babel/runtime-corejs3",
    "pr_number": 17878,
    "pr_sha": "fa796831861231d8496eb44dd85362d2b6f04cae",
    "pr_title": "fix(cli): pass ignore option to chokidar watcher to prevent watching ignored files",
    "pr_url": "https://github.com/babel/babel/pull/17878",
    "result": "skipped",
    "tested_at": "2026-03-25T03:02:55.232Z",
    "run_url": "https://github.com/pieper/forewarn/actions/runs/23522843529"
  },
  "dcmjs-org/dcmjs|babel/babel|17905|600776c64fa73590c9738f21cccf28c505e12f91": {
    "watched_repo": "dcmjs-org/dcmjs",
    "dep_repo": "babel/babel",
    "dep_package": "@babel/runtime-corejs3",
    "pr_number": 17905,
    "pr_sha": "600776c64fa73590c9738f21cccf28c505e12f91",
    "pr_title": "feat: Add ",
    "pr_url": "https://github.com/babel/babel/pull/17905",
    "result": "skipped",
    "tested_at": "2026-03-26T03:04:27.850Z",
    "run_url": "https://github.com/pieper/forewarn/actions/runs/23575413479"
  },
  "dcmjs-org/dcmjs|babel/babel|17486|c30233c09a3dca0b5d63a3d63bf604db44e75f25": {
    "watched_repo": "dcmjs-org/dcmjs",
    "dep_repo": "babel/babel",
    "dep_package": "@babel/runtime-corejs3",
    "pr_number": 17486,
    "pr_sha": "c30233c09a3dca0b5d63a3d63bf604db44e75f25",
    "pr_title": "Allow running tests in child processes",
    "pr_url": "https://github.com/babel/babel/pull/17486",
    "result": "skipped",
    "tested_at": "2026-03-27T03:05:19.327Z",
    "run_url": "https://github.com/pieper/forewarn/actions/runs/23629135542"
  },
  "dcmjs-org/dcmjs|babel/babel|17575|4ba6eb2e6bb44df735f7d42b3286d943fc972317": {
    "watched_repo": "dcmjs-org/dcmjs",
    "dep_repo": "babel/babel",
    "dep_package": "@babel/runtime-corejs3",
    "pr_number": 17575,
    "pr_sha": "4ba6eb2e6bb44df735f7d42b3286d943fc972317",
    "pr_title": "WIP: Try better TS tests for parser",
    "pr_url": "https://github.com/babel/babel/pull/17575",
    "result": "skipped",
    "tested_at": "2026-03-28T03:02:09.094Z",
    "run_url": "https://github.com/pieper/forewarn/actions/runs/23676032482"
  },
  "dcmjs-org/dcmjs|babel/babel|17898|ba5b1e63c61bf7672cdbda49430136db122c98f1": {
    "watched_repo": "dcmjs-org/dcmjs",
    "dep_repo": "babel/babel",
    "dep_package": "@babel/runtime-corejs3",
    "pr_number": 17898,
    "pr_sha": "ba5b1e63c61bf7672cdbda49430136db122c98f1",
    "pr_title": "Report unused eslint directives",
    "pr_url": "https://github.com/babel/babel/pull/17898",
    "result": "skipped",
    "tested_at": "2026-03-29T03:04:40.752Z",
    "run_url": "https://github.com/pieper/forewarn/actions/runs/23700089845"
  },
  "dcmjs-org/dcmjs|babel/babel|17849|4b94a8dff12c91d23fc4d02237c23e01f6bfdd39": {
    "watched_repo": "dcmjs-org/dcmjs",
    "dep_repo": "babel/babel",
    "dep_package": "@babel/runtime-corejs3",
    "pr_number": 17849,
    "pr_sha": "4b94a8dff12c91d23fc4d02237c23e01f6bfdd39",
    "pr_title": "fix(code-frame): use 0-based columns to match Babel AST locations (#1…",
    "pr_url": "https://github.com/babel/babel/pull/17849",
    "result": "skipped",
    "tested_at": "2026-03-30T03:05:13.138Z",
    "run_url": "https://github.com/pieper/forewarn/actions/runs/23726112244"
  },
  "dcmjs-org/dcmjs|babel/babel|17857|6dccbc8e3a5debfb9c1b31c76538a0f8f603f1c9": {
    "watched_repo": "dcmjs-org/dcmjs",
    "dep_repo": "babel/babel",
    "dep_package": "@babel/runtime-corejs3",
    "pr_number": 17857,
    "pr_sha": "6dccbc8e3a5debfb9c1b31c76538a0f8f603f1c9",
    "pr_title": "Support  syntax for Flow type parameter bounds",
    "pr_url": "https://github.com/babel/babel/pull/17857",
    "result": "skipped",
    "tested_at": "2026-03-31T03:05:01.644Z",
    "run_url": "https://github.com/pieper/forewarn/actions/runs/23778451293"
  },
  "dcmjs-org/dcmjs|babel/babel|17740|fab4e920d869f8f8ca6452d99c527463d7fbfbac": {
    "watched_repo": "dcmjs-org/dcmjs",
    "dep_repo": "babel/babel",
    "dep_package": "@babel/runtime-corejs3",
    "pr_number": 17740,
    "pr_sha": "fab4e920d869f8f8ca6452d99c527463d7fbfbac",
    "pr_title": "chore: Add rebase tools",
    "pr_url": "https://github.com/babel/babel/pull/17740",
    "result": "skipped",
    "tested_at": "2026-04-01T03:04:54.123Z",
    "run_url": "https://github.com/pieper/forewarn/actions/runs/23829901809"
  },
  "dcmjs-org/dcmjs|babel/babel|17907|5b9e20a59fa1f7050e0a3b12cacd6c6a7772db1b": {
    "watched_repo": "dcmjs-org/dcmjs",
    "dep_repo": "babel/babel",
    "dep_package": "@babel/runtime-corejs3",
    "pr_number": 17907,
    "pr_sha": "5b9e20a59fa1f7050e0a3b12cacd6c6a7772db1b",
    "pr_title": "Remove ",
    "pr_url": "https://github.com/babel/babel/pull/17907",
    "result": "skipped",
    "tested_at": "2026-04-02T03:04:19.843Z",
    "run_url": "https://github.com/pieper/forewarn/actions/runs/23881685530"
  },
  "dcmjs-org/dcmjs|babel/babel|17897|3dc3c9d0eb529038d5c5f10b9336edf60824c145": {
    "watched_repo": "dcmjs-org/dcmjs",
    "dep_repo": "babel/babel",
    "dep_package": "@babel/runtime-corejs3",
    "pr_number": 17897,
    "pr_sha": "3dc3c9d0eb529038d5c5f10b9336edf60824c145",
    "pr_title": "chore: inline REQUIRED_VERSION(7) special case",
    "pr_url": "https://github.com/babel/babel/pull/17897",
    "result": "skipped",
    "tested_at": "2026-04-03T03:04:30.162Z",
    "run_url": "https://github.com/pieper/forewarn/actions/runs/23931882646"
  },
  "dcmjs-org/dcmjs|babel/babel|17914|9cfffc70c8929457e95fec6d74f5ba55bb52598e": {
    "watched_repo": "dcmjs-org/dcmjs",
    "dep_repo": "babel/babel",
    "dep_package": "@babel/runtime-corejs3",
    "pr_number": 17914,
    "pr_sha": "9cfffc70c8929457e95fec6d74f5ba55bb52598e",
    "pr_title": "chore: Some minor cleaning",
    "pr_url": "https://github.com/babel/babel/pull/17914",
    "result": "skipped",
    "tested_at": "2026-04-04T03:01:23.707Z",
    "run_url": "https://github.com/pieper/forewarn/actions/runs/23969936751"
  },
  "dcmjs-org/dcmjs|babel/babel|17924|8cd1b373e8dcab668b14a1ff9656d0c2d1d5711b": {
    "watched_repo": "dcmjs-org/dcmjs",
    "dep_repo": "babel/babel",
    "dep_package": "@babel/runtime-corejs3",
    "pr_number": 17924,
    "pr_sha": "8cd1b373e8dcab668b14a1ff9656d0c2d1d5711b",
    "pr_title": "Update test262",
    "pr_url": "https://github.com/babel/babel/pull/17924",
    "result": "skipped",
    "tested_at": "2026-04-05T03:04:38.240Z",
    "run_url": "https://github.com/pieper/forewarn/actions/runs/23993043685"
  }
}